sphinx_peek/__init__.py
sphinx_peek/assets/sphinx_peek.css
sphinx_peek/assets/sphinx_peek.js
sphinx_peek-0.0.3.dist-info/LICENSE
sphinx_peek-0.0.3.dist-info/WHEEL
sphinx_peek-0.0.3.dist-info/METADATA
sphinx_peek-0.0.3.dist-info/RECORD
