Metadata-Version: 2.1
Name: sphinx_peek
Version: 0.0.3
Summary: A sphinx extension for peeking at internal references.
Keywords: sphinx,extension,preview
Author-email: Chris Sewell <chrisj_sewell@hotmail.com>
Requires-Python: >=3.8
Classifier: Development Status :: 4 - Beta
Classifier: Framework :: Sphinx :: Extension
Classifier: Intended Audience :: Developers
Classifier: License :: OSI Approved :: MIT License
Classifier: Programming Language :: Python :: 3
Requires-Dist: sphinx
Requires-Dist: furo ; extra == "docs"
Requires-Dist: sphinxcontrib-video ; extra == "docs"
Requires-Dist: pytest ; extra == "testing"
Project-URL: Documentation, https://sphinx-peek.readthedocs.io/
Project-URL: Homepage, https://github.com/sphinx-extensions2/sphinx-peek
Provides-Extra: docs
Provides-Extra: testing
